hello_world/__init__.py
hello_world/main.py
tms_pypi-0.0.1.dist-info/LICENSE
tms_pypi-0.0.1.dist-info/METADATA
tms_pypi-0.0.1.dist-info/WHEEL
tms_pypi-0.0.1.dist-info/top_level.txt
tms_pypi-0.0.1.dist-info/RECORD
