Metadata-Version: 2.1
Name: tms-pypi
Version: 0.0.1
Summary: Tms pypi
Home-page: https://github.com/IAnanevich/tms-python-py43
Author: tms
Author-email: tms@gmail.com
Classifier: Programming Language :: Python :: 3.8
Classifier: License :: OSI Approved :: MIT License
Classifier: Operating System :: OS Independent
Requires-Python: >=3.6
License-File: LICENSE
